.gitignore
MANIFEST.in
README.md
create_git_tag.py
deploy.sh
deployment-requirements.txt
setup.py
version.py
.github/CODEOWNERS
bbc_dslib.egg-info/PKG-INFO
bbc_dslib.egg-info/SOURCES.txt
bbc_dslib.egg-info/dependency_links.txt
bbc_dslib.egg-info/requires.txt
bbc_dslib.egg-info/top_level.txt
dslib/__init__.py
dslib/database/__init__.py
dslib/database/_database.py
dslib/facebook/__init__.py
dslib/facebook/_prophet.py
dslib/google/__init__.py
dslib/google/_bigquery.py
dslib/google/_drive.py
dslib/google/_spreadsheet.py
dslib/google/_storage.py
dslib/science/__init__.py
dslib/science/_pandas.py
dslib/science/_sklearn.py
dslib/utils/__init__.py
dslib/utils/_caching.py
dslib/utils/_io.py
dslib/utils/_logging.py
dslib/utils/_meta.py
dslib/utils/_templating.py
dslib/utils/_temporality.py
img/git_flow.png
scripts/export_to_gcs.py
scripts/import_from_gcs.py
tests/README.md
tests/test_bigquery.py
tests/google/conftest.py
tests/google/test_bigquery.py