Metadata-Version: 2.1
Name: bbc-dslib
Version: 1.2
Summary: A lib for the Data Science team at Blablacar
Home-page: https://github.com/blablacar/data-dslib
Author: Raphaël Berly
Author-email: raphael.berly@blablacar.com
License: closed
Platform: UNKNOWN
Requires-Python: >=3.7.9
Provides-Extra: database
Provides-Extra: facebook
Provides-Extra: google
Provides-Extra: science
Provides-Extra: testing
